{"__symbolic":"module","version":4,"metadata":{"AlphabeticalScrollBarService":{"__symbolic":"class","decorators":[{"__symbolic":"call","expression":{"__symbolic":"reference","module":"@angular/core","name":"Injectable","line":2,"character":1},"arguments":[{"providedIn":"root"}]}],"members":{"__ctor__":[{"__symbolic":"constructor"}]},"statics":{"ɵprov":{}}},"AlphabeticalScrollBarComponent":{"__symbolic":"class","decorators":[{"__symbolic":"call","expression":{"__symbolic":"reference","module":"@angular/core","name":"Component","line":18,"character":1},"arguments":[{"selector":"alphabetical-scroll-bar","changeDetection":{"__symbolic":"select","expression":{"__symbolic":"reference","module":"@angular/core","name":"ChangeDetectionStrategy","line":22,"character":19},"member":"OnPush"},"template":"<div\n  #alphabetContainer\n  class=\"container\"\n  [class.cursor-pointer]=\"!navigateOnHover\"\n>\n  <div\n    *ngFor=\"let letter of visibleLetters; let i = index\"\n    class=\"letter\"\n    [class.letter-disabled]=\"disableInvalidLetters && !isValid(letter)\"\n    [class.letter-is-hidden-value]=\"letter === hiddenLetterValue\"\n    [ngStyle]=\"getLetterStyle(i)\"\n  >\n    <label>{{ letter }}</label>\n  </div>\n</div>\n","styles":[":host{bottom:0;font-size:min(20px,max(12px,1vh));padding:calc(min(20px, max(12px, 1vh))*2) 0;position:absolute;right:-12px;top:0;z-index:1000}:host .container{align-items:center;display:flex;flex-direction:column;height:100%;justify-content:space-between}:host .container.cursor-pointer{cursor:pointer}:host .container .letter{padding:0 20px;pointer-events:none;position:relative;transform-origin:60%;transition:transform .2s ease-in-out}:host .container .letter label{left:50%;position:absolute;top:50%;transform:translate(-50%,-50%)}:host .container .letter.letter-disabled{opacity:.3}:host .container .letter.letter-is-hidden-value{transform:scale(2);transform-origin:center}"]}]}],"members":{"__ctor__":[{"__symbolic":"constructor","parameters":[{"__symbolic":"reference","module":"@angular/core","name":"ChangeDetectorRef","line":25,"character":28}]}],"alphabetContainer":[{"__symbolic":"property","decorators":[{"__symbolic":"call","expression":{"__symbolic":"reference","module":"@angular/core","name":"ViewChild","line":27,"character":3},"arguments":["alphabetContainer",{"static":true}]}]}],"alphabet":[{"__symbolic":"property","decorators":[{"__symbolic":"call","expression":{"__symbolic":"reference","module":"@angular/core","name":"Input","line":34,"character":3}}]}],"overflowDivider":[{"__symbolic":"property","decorators":[{"__symbolic":"call","expression":{"__symbolic":"reference","module":"@angular/core","name":"Input","line":47,"character":3}}]}],"validLetters":[{"__symbolic":"property","decorators":[{"__symbolic":"call","expression":{"__symbolic":"reference","module":"@angular/core","name":"Input","line":58,"character":3}}]}],"disableInvalidLetters":[{"__symbolic":"property","decorators":[{"__symbolic":"call","expression":{"__symbolic":"reference","module":"@angular/core","name":"Input","line":68,"character":3}}]}],"prioritizeHidingInvalidLetters":[{"__symbolic":"property","decorators":[{"__symbolic":"call","expression":{"__symbolic":"reference","module":"@angular/core","name":"Input","line":78,"character":3}}]}],"letterMagnification":[{"__symbolic":"property","decorators":[{"__symbolic":"call","expression":{"__symbolic":"reference","module":"@angular/core","name":"Input","line":88,"character":3}}]}],"magnifyDividers":[{"__symbolic":"property","decorators":[{"__symbolic":"call","expression":{"__symbolic":"reference","module":"@angular/core","name":"Input","line":97,"character":3}}]}],"magnificationMultiplier":[{"__symbolic":"property","decorators":[{"__symbolic":"call","expression":{"__symbolic":"reference","module":"@angular/core","name":"Input","line":106,"character":3}}]}],"magnificationCurve":[{"__symbolic":"property","decorators":[{"__symbolic":"call","expression":{"__symbolic":"reference","module":"@angular/core","name":"Input","line":116,"character":3}}]}],"exactX":[{"__symbolic":"property","decorators":[{"__symbolic":"call","expression":{"__symbolic":"reference","module":"@angular/core","name":"Input","line":127,"character":3}}]}],"navigateOnHover":[{"__symbolic":"property","decorators":[{"__symbolic":"call","expression":{"__symbolic":"reference","module":"@angular/core","name":"Input","line":136,"character":3}}]}],"letterSpacing":[{"__symbolic":"property","decorators":[{"__symbolic":"call","expression":{"__symbolic":"reference","module":"@angular/core","name":"Input","line":145,"character":3}}]}],"letterChange$":[{"__symbolic":"property","decorators":[{"__symbolic":"call","expression":{"__symbolic":"reference","module":"@angular/core","name":"Output","line":160,"character":3},"arguments":["letterChange"]}]}],"isActive$":[{"__symbolic":"property","decorators":[{"__symbolic":"call","expression":{"__symbolic":"reference","module":"@angular/core","name":"Output","line":162,"character":3},"arguments":["isActive"]}]}],"offsetSizeCheckInterval":[{"__symbolic":"property","decorators":[{"__symbolic":"call","expression":{"__symbolic":"reference","module":"@angular/core","name":"Input","line":174,"character":3}}]}],"ngAfterViewInit":[{"__symbolic":"method"}],"ngDoCheck":[{"__symbolic":"method"}],"ngOnDestroy":[{"__symbolic":"method"}],"checkVisibleLetters":[{"__symbolic":"method"}],"getNumHiddenHalves":[{"__symbolic":"method"}],"isValid":[{"__symbolic":"method"}],"getLetterStyle":[{"__symbolic":"method"}],"focusEvent":[{"__symbolic":"method","decorators":[{"__symbolic":"call","expression":{"__symbolic":"reference","module":"@angular/core","name":"HostListener","line":312,"character":3},"arguments":["mousemove",["$event","$event.type"]]},{"__symbolic":"call","expression":{"__symbolic":"reference","module":"@angular/core","name":"HostListener","line":313,"character":3},"arguments":["mouseenter",["$event","$event.type"]]},{"__symbolic":"call","expression":{"__symbolic":"reference","module":"@angular/core","name":"HostListener","line":314,"character":3},"arguments":["touchmove",["$event","$event.type"]]},{"__symbolic":"call","expression":{"__symbolic":"reference","module":"@angular/core","name":"HostListener","line":315,"character":3},"arguments":["touchstart",["$event","$event.type"]]},{"__symbolic":"call","expression":{"__symbolic":"reference","module":"@angular/core","name":"HostListener","line":316,"character":3},"arguments":["click",["$event","$event.type"]]}]}],"focusEnd":[{"__symbolic":"method","decorators":[{"__symbolic":"call","expression":{"__symbolic":"reference","module":"@angular/core","name":"HostListener","line":333,"character":3},"arguments":["mouseleave"]},{"__symbolic":"call","expression":{"__symbolic":"reference","module":"@angular/core","name":"HostListener","line":334,"character":3},"arguments":["touchend"]}]}],"setLetterFromCoordinates":[{"__symbolic":"method"}],"getClosestValidLetterIndex":[{"__symbolic":"method"}],"stringToNumber":[{"__symbolic":"method"}]}},"AlphabeticalScrollBarModule":{"__symbolic":"class","decorators":[{"__symbolic":"call","expression":{"__symbolic":"reference","module":"@angular/core","name":"NgModule","line":6,"character":1},"arguments":[{"declarations":[{"__symbolic":"reference","name":"AlphabeticalScrollBarComponent"}],"imports":[{"__symbolic":"reference","module":"@angular/common","name":"CommonModule","line":9,"character":4}],"exports":[{"__symbolic":"reference","name":"AlphabeticalScrollBarComponent"}]}]}],"members":{}}},"origins":{"AlphabeticalScrollBarService":"./lib/alphabetical-scroll-bar.service","AlphabeticalScrollBarComponent":"./lib/alphabetical-scroll-bar.component","AlphabeticalScrollBarModule":"./lib/alphabetical-scroll-bar.module"},"importAs":"alphabetical-scroll-bar"}